{
    "ar":[
        {
            "startdate":"20230503",
            "fullstartdate":"202305030700",
            "enddate":"20230504",
            "url":"/th?id=OHR.ThreeWildebeest_ROW6956029103_1920x1080.jpg&rf=LaDigue_1920x1080.jpg&pid=hp",
            "urlbase":"/th?id=OHR.ThreeWildebeest_ROW6956029103",
            "copyright":"Wildebeests in the Maasai Mara, Kenya (© Matt Polski/Getty Images)",
            "copyrightlink":"https://www.bing.com/search?q=Wildebeests&form=hpcapt",
            "title":"Info",
            "quiz":"/search?q=Bing+homepage+quiz&filters=WQOskey:%22HPQuiz_20230503_ThreeWildebeest%22&FORM=HPQUIZ",
            "wp":true,
            "hsh":"9e63145df4b7998bb0a8bbc1c19e3170",
            "drk":1,
            "top":1,
            "bot":1,
            "hs":[]
        }
    ],
    "at":[
        {
            "startdate":"20230503",
            "fullstartdate":"202305030700",
            "enddate":"20230504",
            "url":"/th?id=OHR.ThreeWildebeest_ROW6956029103_1920x1080.jpg&rf=LaDigue_1920x1080.jpg&pid=hp",
            "urlbase":"/th?id=OHR.ThreeWildebeest_ROW6956029103",
            "copyright":"Wildebeests in the Maasai Mara, Kenya (© Matt Polski/Getty Images)",
            "copyrightlink":"https://www.bing.com/search?q=Wildebeests&form=hpcapt",
            "title":"Info",
            "quiz":"/search?q=Bing+homepage+quiz&filters=WQOskey:%22HPQuiz_20230503_ThreeWildebeest%22&FORM=HPQUIZ",
            "wp":true,
            "hsh":"9e63145df4b7998bb0a8bbc1c19e3170",
            "drk":1,
            "top":1,
            "bot":1,
            "hs":[]
        }
    ],
    "au":[
        {
            "startdate":"20230503",
            "fullstartdate":"202305030700",
            "enddate":"20230504",
            "url":"/th?id=OHR.ThreeWildebeest_ROW6956029103_1920x1080.jpg&rf=LaDigue_1920x1080.jpg&pid=hp",
            "urlbase":"/th?id=OHR.ThreeWildebeest_ROW6956029103",
            "copyright":"Wildebeests in the Maasai Mara, Kenya (© Matt Polski/Getty Images)",
            "copyrightlink":"https://www.bing.com/search?q=Wildebeests&form=hpcapt&filters=HpDate%3a%2220230503_0700%22",
            "title":"Info",
            "quiz":"/search?q=Bing+homepage+quiz&filters=WQOskey:%22HPQuiz_20230503_ThreeWildebeest%22&FORM=HPQUIZ",
            "wp":true,
            "hsh":"9e63145df4b7998bb0a8bbc1c19e3170",
            "drk":1,
            "top":1,
            "bot":1,
            "hs":[]
        }
    ],
    "be":[
        {
            "startdate":"20230503",
            "fullstartdate":"202305030700",
            "enddate":"20230504",
            "url":"/th?id=OHR.ThreeWildebeest_ROW6956029103_1920x1080.jpg&rf=LaDigue_1920x1080.jpg&pid=hp",
            "urlbase":"/th?id=OHR.ThreeWildebeest_ROW6956029103",
            "copyright":"Wildebeests in the Maasai Mara, Kenya (© Matt Polski/Getty Images)",
            "copyrightlink":"https://www.bing.com/search?q=Wildebeests&form=hpcapt",
            "title":"Info",
            "quiz":"/search?q=Bing+homepage+quiz&filters=WQOskey:%22HPQuiz_20230503_ThreeWildebeest%22&FORM=HPQUIZ",
            "wp":true,
            "hsh":"9cba4d148948266478cd25e7aeb441e3",
            "drk":1,
            "top":1,
            "bot":1,
            "hs":[]
        }
    ],
    "br":[
        {
            "startdate":"20230503",
            "fullstartdate":"202305030300",
            "enddate":"20230504",
            "url":"/th?id=OHR.ThreeWildebeest_PT-BR5590684985_1920x1080.jpg&rf=LaDigue_1920x1080.jpg&pid=hp",
            "urlbase":"/th?id=OHR.ThreeWildebeest_PT-BR5590684985",
            "copyright":"Wildebeests in the Maasai Mara, Kenya (© Matt Polski/Getty Images)",
            "copyrightlink":"https://www.bing.com/search?q=Gnus&form=hpcapt&mkt=pt-br",
            "title":"A grande migração do reino animal",
            "quiz":"/search?q=Bing+homepage+quiz&filters=WQOskey:%22HPQuiz_20230503_ThreeWildebeest%22&FORM=HPQUIZ",
            "wp":true,
            "hsh":"d95135ca8b38161c7bd180123f447625",
            "drk":1,
            "top":1,
            "bot":1,
            "hs":[]
        }
    ],
    "ca":[
        {
            "startdate":"20230503",
            "fullstartdate":"202305030400",
            "enddate":"20230504",
            "url":"/th?id=OHR.ThreeWildebeest_EN-CA3521707205_1920x1080.jpg&rf=LaDigue_1920x1080.jpg&pid=hp",
            "urlbase":"/th?id=OHR.ThreeWildebeest_EN-CA3521707205",
            "copyright":"Wildebeests in the Maasai Mara, Kenya (© Matt Polski/Getty Images)",
            "copyrightlink":"https://www.bing.com/search?q=Wildebeests&form=hpcapt&filters=HpDate%3a%2220230503_0400%22",
            "title":"The animal kingdom's great migration",
            "quiz":"/search?q=Bing+homepage+quiz&filters=WQOskey:%22HPQuiz_20230503_ThreeWildebeest%22&FORM=HPQUIZ",
            "wp":true,
            "hsh":"d6c759c75856172306da522828b39b49",
            "drk":1,
            "top":1,
            "bot":1,
            "hs":[]
        }
    ],
    "ch":[
        {
            "startdate":"20230503",
            "fullstartdate":"202305030700",
            "enddate":"20230504",
            "url":"/th?id=OHR.ThreeWildebeest_ROW6956029103_1920x1080.jpg&rf=LaDigue_1920x1080.jpg&pid=hp",
            "urlbase":"/th?id=OHR.ThreeWildebeest_ROW6956029103",
            "copyright":"Wildebeests in the Maasai Mara, Kenya (© Matt Polski/Getty Images)",
            "copyrightlink":"https://www.bing.com/search?q=Wildebeests&form=hpcapt",
            "title":"Info",
            "quiz":"/search?q=Bing+homepage+quiz&filters=WQOskey:%22HPQuiz_20230503_ThreeWildebeest%22&FORM=HPQUIZ",
            "wp":true,
            "hsh":"9e63145df4b7998bb0a8bbc1c19e3170",
            "drk":1,
            "top":1,
            "bot":1,
            "hs":[]
        }
    ],
    "cl":[
        {
            "startdate":"20230503",
            "fullstartdate":"202305030700",
            "enddate":"20230504",
            "url":"/th?id=OHR.ThreeWildebeest_ROW6956029103_1920x1080.jpg&rf=LaDigue_1920x1080.jpg&pid=hp",
            "urlbase":"/th?id=OHR.ThreeWildebeest_ROW6956029103",
            "copyright":"Wildebeests in the Maasai Mara, Kenya (© Matt Polski/Getty Images)",
            "copyrightlink":"https://www.bing.com/search?q=Wildebeests&form=hpcapt",
            "title":"Info",
            "quiz":"/search?q=Bing+homepage+quiz&filters=WQOskey:%22HPQuiz_20230503_ThreeWildebeest%22&FORM=HPQUIZ",
            "wp":true,
            "hsh":"9e63145df4b7998bb0a8bbc1c19e3170",
            "drk":1,
            "top":1,
            "bot":1,
            "hs":[]
        }
    ],
    "cn":[
        {
            "startdate":"20230503",
            "fullstartdate":"202305031600",
            "enddate":"20230504",
            "url":"/th?id=OHR.RebelBase_ZH-CN0484516261_1920x1080.jpg&rf=LaDigue_1920x1080.jpg&pid=hp",
            "urlbase":"/th?id=OHR.RebelBase_ZH-CN0484516261",
            "copyright":"蒂卡尔的玛雅遗址，危地马拉 (© THP Creative/Getty Images)",
            "copyrightlink":"https://www.bing.com/search?q=%E8%92%82%E5%8D%A1%E5%B0%94%E7%9A%84%E7%8E%9B%E9%9B%85%E9%81%97%E5%9D%80&form=hpcapt&mkt=zh-cn",
            "title":"原力与你同在",
            "quiz":"/search?q=Bing+homepage+quiz&filters=WQOskey:%22HPQuiz_20230503_RebelBase%22&FORM=HPQUIZ",
            "wp":true,
            "hsh":"9f5172cc0ab55d9fd62d32d3f330c856",
            "drk":1,
            "top":1,
            "bot":1,
            "hs":[]
        }
    ],
    "de":[
        {
            "startdate":"20230502",
            "fullstartdate":"202305022200",
            "enddate":"20230503",
            "url":"/th?id=OHR.ThreeWildebeest_DE-DE0436671164_1920x1080.jpg&rf=LaDigue_1920x1080.jpg&pid=hp",
            "urlbase":"/th?id=OHR.ThreeWildebeest_DE-DE0436671164",
            "copyright":"Gnus in der Masai Mara, Kenia (© Matt Polski/Getty Images)",
            "copyrightlink":"https://www.bing.com/search?q=Gnus&form=hpcapt&filters=HpDate%3a%2220230502_2200%22",
            "title":"Die große Wanderung des Tierreichs",
            "quiz":"/search?q=Bing+homepage+quiz&filters=WQOskey:%22HPQuiz_20230502_ThreeWildebeest%22&FORM=HPQUIZ",
            "wp":true,
            "hsh":"8ad4305e9805073150e121e1b896616a",
            "drk":1,
            "top":1,
            "bot":1,
            "hs":[]
        }
    ],
    "dk":[
        {
            "startdate":"20230503",
            "fullstartdate":"202305030700",
            "enddate":"20230504",
            "url":"/th?id=OHR.ThreeWildebeest_ROW6956029103_1920x1080.jpg&rf=LaDigue_1920x1080.jpg&pid=hp",
            "urlbase":"/th?id=OHR.ThreeWildebeest_ROW6956029103",
            "copyright":"Wildebeests in the Maasai Mara, Kenya (© Matt Polski/Getty Images)",
            "copyrightlink":"https://www.bing.com/search?q=Wildebeests&form=hpcapt",
            "title":"Info",
            "quiz":"/search?q=Bing+homepage+quiz&filters=WQOskey:%22HPQuiz_20230503_ThreeWildebeest%22&FORM=HPQUIZ",
            "wp":true,
            "hsh":"9e63145df4b7998bb0a8bbc1c19e3170",
            "drk":1,
            "top":1,
            "bot":1,
            "hs":[]
        }
    ],
    "es":[
        {
            "startdate":"20230502",
            "fullstartdate":"202305022200",
            "enddate":"20230503",
            "url":"/th?id=OHR.ThreeWildebeest_ES-ES8355065020_1920x1080.jpg&rf=LaDigue_1920x1080.jpg&pid=hp",
            "urlbase":"/th?id=OHR.ThreeWildebeest_ES-ES8355065020",
            "copyright":"Ñus en el Maasai Mara, Kenia (© Matt Polski/Getty Images)",
            "copyrightlink":"https://www.bing.com/search?q=%C3%91us&form=hpcapt&filters=HpDate%3a%2220230502_2200%22",
            "title":"La gran migración del reino animal",
            "quiz":"/search?q=Bing+homepage+quiz&filters=WQOskey:%22HPQuiz_20230502_ThreeWildebeest%22&FORM=HPQUIZ",
            "wp":true,
            "hsh":"d9b2257ef75de21995d8993330b7138e",
            "drk":1,
            "top":1,
            "bot":1,
            "hs":[]
        }
    ],
    "fi":[
        {
            "startdate":"20230503",
            "fullstartdate":"202305030700",
            "enddate":"20230504",
            "url":"/th?id=OHR.ThreeWildebeest_ROW6956029103_1920x1080.jpg&rf=LaDigue_1920x1080.jpg&pid=hp",
            "urlbase":"/th?id=OHR.ThreeWildebeest_ROW6956029103",
            "copyright":"Wildebeests in the Maasai Mara, Kenya (© Matt Polski/Getty Images)",
            "copyrightlink":"https://www.bing.com/search?q=Wildebeests&form=hpcapt",
            "title":"Info",
            "quiz":"/search?q=Bing+homepage+quiz&filters=WQOskey:%22HPQuiz_20230503_ThreeWildebeest%22&FORM=HPQUIZ",
            "wp":true,
            "hsh":"9e63145df4b7998bb0a8bbc1c19e3170",
            "drk":1,
            "top":1,
            "bot":1,
            "hs":[]
        }
    ],
    "fr":[
        {
            "startdate":"20230502",
            "fullstartdate":"202305022200",
            "enddate":"20230503",
            "url":"/th?id=OHR.ThreeWildebeest_FR-FR9059959513_1920x1080.jpg&rf=LaDigue_1920x1080.jpg&pid=hp",
            "urlbase":"/th?id=OHR.ThreeWildebeest_FR-FR9059959513",
            "copyright":"Gnous dans le Masaï Mara, Kenya (© Matt Polski/Getty Images)",
            "copyrightlink":"https://www.bing.com/search?q=gnous&form=hpcapt&filters=HpDate%3a%2220230502_2200%22",
            "title":"La grande migration du règne animal",
            "quiz":"/search?q=Bing+homepage+quiz&filters=WQOskey:%22HPQuiz_20230502_ThreeWildebeest%22&FORM=HPQUIZ",
            "wp":true,
            "hsh":"5610c0c4eccb30f08a4f0ac0e8717da2",
            "drk":1,
            "top":1,
            "bot":1,
            "hs":[]
        }
    ],
    "hk":[
        {
            "startdate":"20230503",
            "fullstartdate":"202305030700",
            "enddate":"20230504",
            "url":"/th?id=OHR.ThreeWildebeest_ROW6956029103_1920x1080.jpg&rf=LaDigue_1920x1080.jpg&pid=hp",
            "urlbase":"/th?id=OHR.ThreeWildebeest_ROW6956029103",
            "copyright":"Wildebeests in the Maasai Mara, Kenya (© Matt Polski/Getty Images)",
            "copyrightlink":"https://www.bing.com/search?q=Wildebeests&form=hpcapt",
            "title":"Info",
            "quiz":"/search?q=Bing+homepage+quiz&filters=WQOskey:%22HPQuiz_20230503_ThreeWildebeest%22&FORM=HPQUIZ",
            "wp":true,
            "hsh":"9e63145df4b7998bb0a8bbc1c19e3170",
            "drk":1,
            "top":1,
            "bot":1,
            "hs":[]
        }
    ],
    "ie":[
        {
            "startdate":"20230503",
            "fullstartdate":"202305030700",
            "enddate":"20230504",
            "url":"/th?id=OHR.ThreeWildebeest_ROW6956029103_1920x1080.jpg&rf=LaDigue_1920x1080.jpg&pid=hp",
            "urlbase":"/th?id=OHR.ThreeWildebeest_ROW6956029103",
            "copyright":"Wildebeests in the Maasai Mara, Kenya (© Matt Polski/Getty Images)",
            "copyrightlink":"https://www.bing.com/search?q=Wildebeests&form=hpcapt",
            "title":"Info",
            "quiz":"/search?q=Bing+homepage+quiz&filters=WQOskey:%22HPQuiz_20230503_ThreeWildebeest%22&FORM=HPQUIZ",
            "wp":true,
            "hsh":"9e63145df4b7998bb0a8bbc1c19e3170",
            "drk":1,
            "top":1,
            "bot":1,
            "hs":[]
        }
    ],
    "in":[
        {
            "startdate":"20230502",
            "fullstartdate":"202305021830",
            "enddate":"20230503",
            "url":"/th?id=OHR.ThreeWildebeest_EN-IN5007825213_1920x1080.jpg&rf=LaDigue_1920x1080.jpg&pid=hp",
            "urlbase":"/th?id=OHR.ThreeWildebeest_EN-IN5007825213",
            "copyright":"Wildebeests in the Maasai Mara, Kenya (© Matt Polski/Getty Images)",
            "copyrightlink":"https://www.bing.com/search?q=Wildebeests&form=hpcapt&filters=HpDate%3a%2220230502_1830%22",
            "title":"The animal kingdom's great migration",
            "quiz":"/search?q=Bing+homepage+quiz&filters=WQOskey:%22HPQuiz_20230502_ThreeWildebeest%22&FORM=HPQUIZ",
            "wp":true,
            "hsh":"f710193f4086036fe1898b6f7aa077d2",
            "drk":1,
            "top":1,
            "bot":1,
            "hs":[]
        }
    ],
    "it":[
        {
            "startdate":"20230502",
            "fullstartdate":"202305022200",
            "enddate":"20230503",
            "url":"/th?id=OHR.ThreeWildebeest_IT-IT3805881299_1920x1080.jpg&rf=LaDigue_1920x1080.jpg&pid=hp",
            "urlbase":"/th?id=OHR.ThreeWildebeest_IT-IT3805881299",
            "copyright":"Gnu nel Maasai Mara, Kenya (© Matt Polski/Getty Images)",
            "copyrightlink":"https://www.bing.com/search?q=gnu+animale&form=hpcapt",
            "title":"Dove stanno andando questi gnu?",
            "quiz":"/search?q=Bing+homepage+quiz&filters=WQOskey:%22HPQuiz_20230502_ThreeWildebeest%22&FORM=HPQUIZ",
            "wp":true,
            "hsh":"b11e4046a3b895de97a819f12541f003",
            "drk":1,
            "top":1,
            "bot":1,
            "hs":[]
        }
    ],
    "jp":[
        {
            "startdate":"20230503",
            "fullstartdate":"202305031500",
            "enddate":"20230504",
            "url":"/th?id=OHR.RebelBase_JA-JP2351113050_1920x1080.jpg&rf=LaDigue_1920x1080.jpg&pid=hp",
            "urlbase":"/th?id=OHR.RebelBase_JA-JP2351113050",
            "copyright":"ティカル国立公園にあるマヤ遺跡, グアテマラ (© THP Creative/Getty Images)",
            "copyrightlink":"https://www.bing.com/search?q=%E3%83%86%E3%82%A3%E3%82%AB%E3%83%AB%E5%9B%BD%E7%AB%8B%E5%85%AC%E5%9C%92&form=hpcapt&filters=HpDate%3a%2220230503_1500%22",
            "title":"今日はスター・ウォーズの日",
            "quiz":"/search?q=Bing+homepage+quiz&filters=WQOskey:%22HPQuiz_20230503_RebelBase%22&FORM=HPQUIZ",
            "wp":true,
            "hsh":"9202a789959aacd3d512698ea9074692",
            "drk":1,
            "top":1,
            "bot":1,
            "hs":[]
        }
    ],
    "kr":[
        {
            "startdate":"20230503",
            "fullstartdate":"202305030700",
            "enddate":"20230504",
            "url":"/th?id=OHR.ThreeWildebeest_ROW6956029103_1920x1080.jpg&rf=LaDigue_1920x1080.jpg&pid=hp",
            "urlbase":"/th?id=OHR.ThreeWildebeest_ROW6956029103",
            "copyright":"Wildebeests in the Maasai Mara, Kenya (© Matt Polski/Getty Images)",
            "copyrightlink":"https://www.bing.com/search?q=Wildebeests&form=hpcapt",
            "title":"Info",
            "quiz":"/search?q=Bing+homepage+quiz&filters=WQOskey:%22HPQuiz_20230503_ThreeWildebeest%22&FORM=HPQUIZ",
            "wp":true,
            "hsh":"9e63145df4b7998bb0a8bbc1c19e3170",
            "drk":1,
            "top":1,
            "bot":1,
            "hs":[]
        }
    ],
    "nl":[
        {
            "startdate":"20230503",
            "fullstartdate":"202305030700",
            "enddate":"20230504",
            "url":"/th?id=OHR.ThreeWildebeest_ROW6956029103_1920x1080.jpg&rf=LaDigue_1920x1080.jpg&pid=hp",
            "urlbase":"/th?id=OHR.ThreeWildebeest_ROW6956029103",
            "copyright":"Wildebeests in the Maasai Mara, Kenya (© Matt Polski/Getty Images)",
            "copyrightlink":"https://www.bing.com/search?q=Wildebeests&form=hpcapt",
            "title":"Info",
            "quiz":"/search?q=Bing+homepage+quiz&filters=WQOskey:%22HPQuiz_20230503_ThreeWildebeest%22&FORM=HPQUIZ",
            "wp":true,
            "hsh":"9e63145df4b7998bb0a8bbc1c19e3170",
            "drk":1,
            "top":1,
            "bot":1,
            "hs":[]
        }
    ],
    "no":[
        {
            "startdate":"20230503",
            "fullstartdate":"202305030700",
            "enddate":"20230504",
            "url":"/th?id=OHR.ThreeWildebeest_ROW6956029103_1920x1080.jpg&rf=LaDigue_1920x1080.jpg&pid=hp",
            "urlbase":"/th?id=OHR.ThreeWildebeest_ROW6956029103",
            "copyright":"Wildebeests in the Maasai Mara, Kenya (© Matt Polski/Getty Images)",
            "copyrightlink":"https://www.bing.com/search?q=Wildebeests&form=hpcapt",
            "title":"Info",
            "quiz":"/search?q=Bing+homepage+quiz&filters=WQOskey:%22HPQuiz_20230503_ThreeWildebeest%22&FORM=HPQUIZ",
            "wp":true,
            "hsh":"9e63145df4b7998bb0a8bbc1c19e3170",
            "drk":1,
            "top":1,
            "bot":1,
            "hs":[]
        }
    ],
    "nz":[
        {
            "startdate":"20230503",
            "fullstartdate":"202305030700",
            "enddate":"20230504",
            "url":"/th?id=OHR.ThreeWildebeest_ROW6956029103_1920x1080.jpg&rf=LaDigue_1920x1080.jpg&pid=hp",
            "urlbase":"/th?id=OHR.ThreeWildebeest_ROW6956029103",
            "copyright":"Wildebeests in the Maasai Mara, Kenya (© Matt Polski/Getty Images)",
            "copyrightlink":"https://www.bing.com/search?q=Wildebeests&form=hpcapt",
            "title":"Info",
            "quiz":"/search?q=Bing+homepage+quiz&filters=WQOskey:%22HPQuiz_20230503_ThreeWildebeest%22&FORM=HPQUIZ",
            "wp":true,
            "hsh":"9e63145df4b7998bb0a8bbc1c19e3170",
            "drk":1,
            "top":1,
            "bot":1,
            "hs":[]
        }
    ],
    "ph":[
        {
            "startdate":"20230503",
            "fullstartdate":"202305030700",
            "enddate":"20230504",
            "url":"/th?id=OHR.ThreeWildebeest_ROW6956029103_1920x1080.jpg&rf=LaDigue_1920x1080.jpg&pid=hp",
            "urlbase":"/th?id=OHR.ThreeWildebeest_ROW6956029103",
            "copyright":"Wildebeests in the Maasai Mara, Kenya (© Matt Polski/Getty Images)",
            "copyrightlink":"https://www.bing.com/search?q=Wildebeests&form=hpcapt",
            "title":"Info",
            "quiz":"/search?q=Bing+homepage+quiz&filters=WQOskey:%22HPQuiz_20230503_ThreeWildebeest%22&FORM=HPQUIZ",
            "wp":true,
            "hsh":"9e63145df4b7998bb0a8bbc1c19e3170",
            "drk":1,
            "top":1,
            "bot":1,
            "hs":[]
        }
    ],
    "pt":[
        {
            "startdate":"20230503",
            "fullstartdate":"202305030700",
            "enddate":"20230504",
            "url":"/th?id=OHR.ThreeWildebeest_ROW6956029103_1920x1080.jpg&rf=LaDigue_1920x1080.jpg&pid=hp",
            "urlbase":"/th?id=OHR.ThreeWildebeest_ROW6956029103",
            "copyright":"Wildebeests in the Maasai Mara, Kenya (© Matt Polski/Getty Images)",
            "copyrightlink":"https://www.bing.com/search?q=Wildebeests&form=hpcapt",
            "title":"Info",
            "quiz":"/search?q=Bing+homepage+quiz&filters=WQOskey:%22HPQuiz_20230503_ThreeWildebeest%22&FORM=HPQUIZ",
            "wp":true,
            "hsh":"9cba4d148948266478cd25e7aeb441e3",
            "drk":1,
            "top":1,
            "bot":1,
            "hs":[]
        }
    ],
    "ru":[
        {
            "startdate":"20230503",
            "fullstartdate":"202305030700",
            "enddate":"20230504",
            "url":"/th?id=OHR.ThreeWildebeest_ROW6956029103_1920x1080.jpg&rf=LaDigue_1920x1080.jpg&pid=hp",
            "urlbase":"/th?id=OHR.ThreeWildebeest_ROW6956029103",
            "copyright":"Wildebeests in the Maasai Mara, Kenya (© Matt Polski/Getty Images)",
            "copyrightlink":"https://www.bing.com/search?q=Wildebeests&form=hpcapt",
            "title":"Info",
            "quiz":"/search?q=Bing+homepage+quiz&filters=WQOskey:%22HPQuiz_20230503_ThreeWildebeest%22&FORM=HPQUIZ",
            "wp":true,
            "hsh":"9e63145df4b7998bb0a8bbc1c19e3170",
            "drk":1,
            "top":1,
            "bot":1,
            "hs":[]
        }
    ],
    "se":[
        {
            "startdate":"20230503",
            "fullstartdate":"202305030700",
            "enddate":"20230504",
            "url":"/th?id=OHR.ThreeWildebeest_ROW6956029103_1920x1080.jpg&rf=LaDigue_1920x1080.jpg&pid=hp",
            "urlbase":"/th?id=OHR.ThreeWildebeest_ROW6956029103",
            "copyright":"Wildebeests in the Maasai Mara, Kenya (© Matt Polski/Getty Images)",
            "copyrightlink":"https://www.bing.com/search?q=Wildebeests&form=hpcapt",
            "title":"Info",
            "quiz":"/search?q=Bing+homepage+quiz&filters=WQOskey:%22HPQuiz_20230503_ThreeWildebeest%22&FORM=HPQUIZ",
            "wp":true,
            "hsh":"9e63145df4b7998bb0a8bbc1c19e3170",
            "drk":1,
            "top":1,
            "bot":1,
            "hs":[]
        }
    ],
    "sg":[
        {
            "startdate":"20230503",
            "fullstartdate":"202305030700",
            "enddate":"20230504",
            "url":"/th?id=OHR.ThreeWildebeest_ROW6956029103_1920x1080.jpg&rf=LaDigue_1920x1080.jpg&pid=hp",
            "urlbase":"/th?id=OHR.ThreeWildebeest_ROW6956029103",
            "copyright":"Wildebeests in the Maasai Mara, Kenya (© Matt Polski/Getty Images)",
            "copyrightlink":"https://www.bing.com/search?q=Wildebeests&form=hpcapt",
            "title":"Info",
            "quiz":"/search?q=Bing+homepage+quiz&filters=WQOskey:%22HPQuiz_20230503_ThreeWildebeest%22&FORM=HPQUIZ",
            "wp":true,
            "hsh":"9e63145df4b7998bb0a8bbc1c19e3170",
            "drk":1,
            "top":1,
            "bot":1,
            "hs":[]
        }
    ],
    "tw":[
        {
            "startdate":"20230503",
            "fullstartdate":"202305030700",
            "enddate":"20230504",
            "url":"/th?id=OHR.ThreeWildebeest_ROW6956029103_1920x1080.jpg&rf=LaDigue_1920x1080.jpg&pid=hp",
            "urlbase":"/th?id=OHR.ThreeWildebeest_ROW6956029103",
            "copyright":"Wildebeests in the Maasai Mara, Kenya (© Matt Polski/Getty Images)",
            "copyrightlink":"https://www.bing.com/search?q=Wildebeests&form=hpcapt",
            "title":"Info",
            "quiz":"/search?q=Bing+homepage+quiz&filters=WQOskey:%22HPQuiz_20230503_ThreeWildebeest%22&FORM=HPQUIZ",
            "wp":true,
            "hsh":"9e63145df4b7998bb0a8bbc1c19e3170",
            "drk":1,
            "top":1,
            "bot":1,
            "hs":[]
        }
    ],
    "uk":[
        {
            "startdate":"20230503",
            "fullstartdate":"202305031500",
            "enddate":"20230504",
            "url":"/th?id=OHR.RebelBase_JA-JP2351113050_1920x1080.jpg&rf=LaDigue_1920x1080.jpg&pid=hp",
            "urlbase":"/th?id=OHR.RebelBase_JA-JP2351113050",
            "copyright":"ティカル国立公園にあるマヤ遺跡, グアテマラ (© THP Creative/Getty Images)",
            "copyrightlink":"https://www.bing.com/search?q=%E3%83%86%E3%82%A3%E3%82%AB%E3%83%AB%E5%9B%BD%E7%AB%8B%E5%85%AC%E5%9C%92&form=hpcapt&filters=HpDate%3a%2220230503_1500%22",
            "title":"今日はスター・ウォーズの日",
            "quiz":"/search?q=Bing+homepage+quiz&filters=WQOskey:%22HPQuiz_20230503_RebelBase%22&FORM=HPQUIZ",
            "wp":true,
            "hsh":"9202a789959aacd3d512698ea9074692",
            "drk":1,
            "top":1,
            "bot":1,
            "hs":[]
        }
    ]
}