{
    "ar":[
        {
            "startdate":"20220314",
            "fullstartdate":"202203140700",
            "enddate":"20220315",
            "url":"/th?id=OHR.LanyonQuoit_ROW1211200542_1920x1080.jpg&rf=LaDigue_1920x1080.jpg&pid=hp",
            "urlbase":"/th?id=OHR.LanyonQuoit_ROW1211200542",
            "copyright":"Lanyon Quoit, Cornwall, England (© Guy Edwardes/Minden Pictures)",
            "copyrightlink":"https://www.bing.com/search?q=lanyon+quoit+cornwall&form=hpcapt",
            "title":"Info",
            "quiz":"/search?q=Bing+homepage+quiz&filters=WQOskey:%22HPQuiz_20220314_LanyonQuoit%22&FORM=HPQUIZ",
            "wp":true,
            "hsh":"13884c0db8f5f7b10c81944abc60908e",
            "drk":1,
            "top":1,
            "bot":1,
            "hs":[]
        }
    ],
    "at":[
        {
            "startdate":"20220314",
            "fullstartdate":"202203140700",
            "enddate":"20220315",
            "url":"/th?id=OHR.LanyonQuoit_ROW1211200542_1920x1080.jpg&rf=LaDigue_1920x1080.jpg&pid=hp",
            "urlbase":"/th?id=OHR.LanyonQuoit_ROW1211200542",
            "copyright":"Lanyon Quoit, Cornwall, England (© Guy Edwardes/Minden Pictures)",
            "copyrightlink":"https://www.bing.com/search?q=lanyon+quoit+cornwall&form=hpcapt",
            "title":"Info",
            "quiz":"/search?q=Bing+homepage+quiz&filters=WQOskey:%22HPQuiz_20220314_LanyonQuoit%22&FORM=HPQUIZ",
            "wp":true,
            "hsh":"13884c0db8f5f7b10c81944abc60908e",
            "drk":1,
            "top":1,
            "bot":1,
            "hs":[]
        }
    ],
    "au":[
        {
            "startdate":"20220314",
            "fullstartdate":"202203140700",
            "enddate":"20220315",
            "url":"/th?id=OHR.LanyonQuoit_ROW1211200542_1920x1080.jpg&rf=LaDigue_1920x1080.jpg&pid=hp",
            "urlbase":"/th?id=OHR.LanyonQuoit_ROW1211200542",
            "copyright":"Lanyon Quoit, Cornwall, England (© Guy Edwardes/Minden Pictures)",
            "copyrightlink":"https://www.bing.com/search?q=lanyon+quoit+cornwall&form=hpcapt&filters=HpDate%3a%2220220314_0700%22",
            "title":"Info",
            "quiz":"/search?q=Bing+homepage+quiz&filters=WQOskey:%22HPQuiz_20220314_LanyonQuoit%22&FORM=HPQUIZ",
            "wp":true,
            "hsh":"13884c0db8f5f7b10c81944abc60908e",
            "drk":1,
            "top":1,
            "bot":1,
            "hs":[]
        }
    ],
    "be":[
        {
            "startdate":"20220314",
            "fullstartdate":"202203140700",
            "enddate":"20220315",
            "url":"/th?id=OHR.LanyonQuoit_ROW1211200542_1920x1080.jpg&rf=LaDigue_1920x1080.jpg&pid=hp",
            "urlbase":"/th?id=OHR.LanyonQuoit_ROW1211200542",
            "copyright":"Lanyon Quoit, Cornwall, England (© Guy Edwardes/Minden Pictures)",
            "copyrightlink":"https://www.bing.com/search?q=lanyon+quoit+cornwall&form=hpcapt",
            "title":"Info",
            "quiz":"/search?q=Bing+homepage+quiz&filters=WQOskey:%22HPQuiz_20220314_LanyonQuoit%22&FORM=HPQUIZ",
            "wp":true,
            "hsh":"13884c0db8f5f7b10c81944abc60908e",
            "drk":1,
            "top":1,
            "bot":1,
            "hs":[]
        }
    ],
    "br":[
        {
            "startdate":"20220314",
            "fullstartdate":"202203140700",
            "enddate":"20220315",
            "url":"/th?id=OHR.LanyonQuoit_ROW1211200542_1920x1080.jpg&rf=LaDigue_1920x1080.jpg&pid=hp",
            "urlbase":"/th?id=OHR.LanyonQuoit_ROW1211200542",
            "copyright":"Lanyon Quoit, Cornwall, England (© Guy Edwardes/Minden Pictures)",
            "copyrightlink":"https://www.bing.com/search?q=lanyon+quoit+cornwall&form=hpcapt",
            "title":"Info",
            "quiz":"/search?q=Bing+homepage+quiz&filters=WQOskey:%22HPQuiz_20220314_LanyonQuoit%22&FORM=HPQUIZ",
            "wp":true,
            "hsh":"13884c0db8f5f7b10c81944abc60908e",
            "drk":1,
            "top":1,
            "bot":1,
            "hs":[]
        }
    ],
    "ca":[
        {
            "startdate":"20220314",
            "fullstartdate":"202203140400",
            "enddate":"20220315",
            "url":"/th?id=OHR.LanyonQuoit_EN-CA8546163516_1920x1080.jpg&rf=LaDigue_1920x1080.jpg&pid=hp",
            "urlbase":"/th?id=OHR.LanyonQuoit_EN-CA8546163516",
            "copyright":"Lanyon Quoit burial chamber, Cornwall, England (© Guy Edwardes/Minden Pictures)",
            "copyrightlink":"https://www.bing.com/search?q=Pi+Day+history&form=hpcapt&filters=HpDate%3a%2220220314_0400%22",
            "title":"It’s just pi in the sky...",
            "quiz":"/search?q=Bing+homepage+quiz&filters=WQOskey:%22HPQuiz_20220314_LanyonQuoit%22&FORM=HPQUIZ",
            "wp":true,
            "hsh":"1496c7aaca0900b17e266e2b89d9dffb",
            "drk":1,
            "top":1,
            "bot":1,
            "hs":[]
        }
    ],
    "ch":[
        {
            "startdate":"20220314",
            "fullstartdate":"202203140700",
            "enddate":"20220315",
            "url":"/th?id=OHR.LanyonQuoit_ROW1211200542_1920x1080.jpg&rf=LaDigue_1920x1080.jpg&pid=hp",
            "urlbase":"/th?id=OHR.LanyonQuoit_ROW1211200542",
            "copyright":"Lanyon Quoit, Cornwall, England (© Guy Edwardes/Minden Pictures)",
            "copyrightlink":"https://www.bing.com/search?q=lanyon+quoit+cornwall&form=hpcapt",
            "title":"Info",
            "quiz":"/search?q=Bing+homepage+quiz&filters=WQOskey:%22HPQuiz_20220314_LanyonQuoit%22&FORM=HPQUIZ",
            "wp":true,
            "hsh":"13884c0db8f5f7b10c81944abc60908e",
            "drk":1,
            "top":1,
            "bot":1,
            "hs":[]
        }
    ],
    "cl":[
        {
            "startdate":"20220314",
            "fullstartdate":"202203140700",
            "enddate":"20220315",
            "url":"/th?id=OHR.LanyonQuoit_ROW1211200542_1920x1080.jpg&rf=LaDigue_1920x1080.jpg&pid=hp",
            "urlbase":"/th?id=OHR.LanyonQuoit_ROW1211200542",
            "copyright":"Lanyon Quoit, Cornwall, England (© Guy Edwardes/Minden Pictures)",
            "copyrightlink":"https://www.bing.com/search?q=lanyon+quoit+cornwall&form=hpcapt",
            "title":"Info",
            "quiz":"/search?q=Bing+homepage+quiz&filters=WQOskey:%22HPQuiz_20220314_LanyonQuoit%22&FORM=HPQUIZ",
            "wp":true,
            "hsh":"13884c0db8f5f7b10c81944abc60908e",
            "drk":1,
            "top":1,
            "bot":1,
            "hs":[]
        }
    ],
    "cn":[
        {
            "startdate":"20220314",
            "fullstartdate":"202203141600",
            "enddate":"20220315",
            "url":"/th?id=OHR.RomanView_ZH-CN6469652448_1920x1080.jpg&rf=LaDigue_1920x1080.jpg&pid=hp",
            "urlbase":"/th?id=OHR.RomanView_ZH-CN6469652448",
            "copyright":"古罗马广场，意大利 (© Peter Zelei Images/Getty Images)",
            "copyrightlink":"https://www.bing.com/search?q=%E5%8F%A4%E7%BD%97%E9%A9%AC%E5%B9%BF%E5%9C%BA&form=hpcapt&mkt=zh-cn",
            "title":"前往罗马广场的路上发生了一件趣事……",
            "quiz":"/search?q=Bing+homepage+quiz&filters=WQOskey:%22HPQuiz_20220314_RomanView%22&FORM=HPQUIZ",
            "wp":true,
            "hsh":"26cf395c099779a5e2494430389f9fac",
            "drk":1,
            "top":1,
            "bot":1,
            "hs":[]
        }
    ],
    "de":[
        {
            "startdate":"20220313",
            "fullstartdate":"202203132300",
            "enddate":"20220314",
            "url":"/th?id=OHR.LanyonQuoit_DE-DE2402126177_1920x1080.jpg&rf=LaDigue_1920x1080.jpg&pid=hp",
            "urlbase":"/th?id=OHR.LanyonQuoit_DE-DE2402126177",
            "copyright":"Das Großsteingrab Lanyon Quoit in Cornwall, England, Vereinigtes Königreich (© Guy Edwardes/Minden Pictures)",
            "copyrightlink":"https://www.bing.com/search?q=Pi-Tag&form=hpcapt&filters=HpDate%3a%2220220313_2300%22",
            "title":"Welche Zahl wird heute gefeiert?",
            "quiz":"/search?q=Bing+homepage+quiz&filters=WQOskey:%22HPQuiz_20220313_LanyonQuoit%22&FORM=HPQUIZ",
            "wp":true,
            "hsh":"9f11988b205aef427ee7a7002509d48d",
            "drk":1,
            "top":1,
            "bot":1,
            "hs":[]
        }
    ],
    "dk":[
        {
            "startdate":"20220314",
            "fullstartdate":"202203140700",
            "enddate":"20220315",
            "url":"/th?id=OHR.LanyonQuoit_ROW1211200542_1920x1080.jpg&rf=LaDigue_1920x1080.jpg&pid=hp",
            "urlbase":"/th?id=OHR.LanyonQuoit_ROW1211200542",
            "copyright":"Lanyon Quoit, Cornwall, England (© Guy Edwardes/Minden Pictures)",
            "copyrightlink":"https://www.bing.com/search?q=lanyon+quoit+cornwall&form=hpcapt",
            "title":"Info",
            "quiz":"/search?q=Bing+homepage+quiz&filters=WQOskey:%22HPQuiz_20220314_LanyonQuoit%22&FORM=HPQUIZ",
            "wp":true,
            "hsh":"13884c0db8f5f7b10c81944abc60908e",
            "drk":1,
            "top":1,
            "bot":1,
            "hs":[]
        }
    ],
    "es":[
        {
            "startdate":"20220314",
            "fullstartdate":"202203140700",
            "enddate":"20220315",
            "url":"/th?id=OHR.LanyonQuoit_ROW1211200542_1920x1080.jpg&rf=LaDigue_1920x1080.jpg&pid=hp",
            "urlbase":"/th?id=OHR.LanyonQuoit_ROW1211200542",
            "copyright":"Lanyon Quoit, Cornwall, England (© Guy Edwardes/Minden Pictures)",
            "copyrightlink":"https://www.bing.com/search?q=lanyon+quoit+cornwall&form=hpcapt&filters=HpDate%3a%2220220314_0700%22",
            "title":"Info",
            "quiz":"/search?q=Bing+homepage+quiz&filters=WQOskey:%22HPQuiz_20220314_LanyonQuoit%22&FORM=HPQUIZ",
            "wp":true,
            "hsh":"13884c0db8f5f7b10c81944abc60908e",
            "drk":1,
            "top":1,
            "bot":1,
            "hs":[]
        }
    ],
    "fi":[
        {
            "startdate":"20220314",
            "fullstartdate":"202203140700",
            "enddate":"20220315",
            "url":"/th?id=OHR.LanyonQuoit_ROW1211200542_1920x1080.jpg&rf=LaDigue_1920x1080.jpg&pid=hp",
            "urlbase":"/th?id=OHR.LanyonQuoit_ROW1211200542",
            "copyright":"Lanyon Quoit, Cornwall, England (© Guy Edwardes/Minden Pictures)",
            "copyrightlink":"https://www.bing.com/search?q=lanyon+quoit+cornwall&form=hpcapt",
            "title":"Info",
            "quiz":"/search?q=Bing+homepage+quiz&filters=WQOskey:%22HPQuiz_20220314_LanyonQuoit%22&FORM=HPQUIZ",
            "wp":true,
            "hsh":"13884c0db8f5f7b10c81944abc60908e",
            "drk":1,
            "top":1,
            "bot":1,
            "hs":[]
        }
    ],
    "fr":[
        {
            "startdate":"20220313",
            "fullstartdate":"202203132300",
            "enddate":"20220314",
            "url":"/th?id=OHR.LanyonQuoit_FR-FR5001111498_1920x1080.jpg&rf=LaDigue_1920x1080.jpg&pid=hp",
            "urlbase":"/th?id=OHR.LanyonQuoit_FR-FR5001111498",
            "copyright":"Chambre funéraire Lanyon Quoit, Cornouailles, Angleterre (© Guy Edwardes/Minden Pictures)",
            "copyrightlink":"https://www.bing.com/search?q=Journ%C3%A9e+de+pi+&form=hpcapt&filters=HpDate%3a%2220220313_2300%22",
            "title":"Pi où on ne l’attendait pas",
            "quiz":"/search?q=Bing+homepage+quiz&filters=WQOskey:%22HPQuiz_20220313_LanyonQuoit%22&FORM=HPQUIZ",
            "wp":true,
            "hsh":"ccba9a97c9d4c542de0650d3641db96d",
            "drk":1,
            "top":1,
            "bot":1,
            "hs":[]
        }
    ],
    "hk":[
        {
            "startdate":"20220314",
            "fullstartdate":"202203140700",
            "enddate":"20220315",
            "url":"/th?id=OHR.LanyonQuoit_ROW1211200542_1920x1080.jpg&rf=LaDigue_1920x1080.jpg&pid=hp",
            "urlbase":"/th?id=OHR.LanyonQuoit_ROW1211200542",
            "copyright":"Lanyon Quoit, Cornwall, England (© Guy Edwardes/Minden Pictures)",
            "copyrightlink":"https://www.bing.com/search?q=lanyon+quoit+cornwall&form=hpcapt",
            "title":"Info",
            "quiz":"/search?q=Bing+homepage+quiz&filters=WQOskey:%22HPQuiz_20220314_LanyonQuoit%22&FORM=HPQUIZ",
            "wp":true,
            "hsh":"13884c0db8f5f7b10c81944abc60908e",
            "drk":1,
            "top":1,
            "bot":1,
            "hs":[]
        }
    ],
    "ie":[
        {
            "startdate":"20220314",
            "fullstartdate":"202203140700",
            "enddate":"20220315",
            "url":"/th?id=OHR.LanyonQuoit_ROW1211200542_1920x1080.jpg&rf=LaDigue_1920x1080.jpg&pid=hp",
            "urlbase":"/th?id=OHR.LanyonQuoit_ROW1211200542",
            "copyright":"Lanyon Quoit, Cornwall, England (© Guy Edwardes/Minden Pictures)",
            "copyrightlink":"https://www.bing.com/search?q=lanyon+quoit+cornwall&form=hpcapt",
            "title":"Info",
            "quiz":"/search?q=Bing+homepage+quiz&filters=WQOskey:%22HPQuiz_20220314_LanyonQuoit%22&FORM=HPQUIZ",
            "wp":true,
            "hsh":"13884c0db8f5f7b10c81944abc60908e",
            "drk":1,
            "top":1,
            "bot":1,
            "hs":[]
        }
    ],
    "in":[
        {
            "startdate":"20220314",
            "fullstartdate":"202203141830",
            "enddate":"20220315",
            "url":"/th?id=OHR.RomanView_EN-IN2009107581_1920x1080.jpg&rf=LaDigue_1920x1080.jpg&pid=hp",
            "urlbase":"/th?id=OHR.RomanView_EN-IN2009107581",
            "copyright":"The Roman Forum, Rome, Italy (© Peter Zelei Images/Getty Images)",
            "copyrightlink":"https://www.bing.com/search?q=Roman+Forum&form=hpcapt&filters=HpDate%3a%2220220314_1830%22",
            "title":"A funny thing happened on the way to the Forum…",
            "quiz":"/search?q=Bing+homepage+quiz&filters=WQOskey:%22HPQuiz_20220314_RomanView%22&FORM=HPQUIZ",
            "wp":true,
            "hsh":"ce9b48945d8a6cbbc38924f69be98c1b",
            "drk":1,
            "top":1,
            "bot":1,
            "hs":[]
        }
    ],
    "it":[
        {
            "startdate":"20220314",
            "fullstartdate":"202203140700",
            "enddate":"20220315",
            "url":"/th?id=OHR.LanyonQuoit_ROW1211200542_1920x1080.jpg&rf=LaDigue_1920x1080.jpg&pid=hp",
            "urlbase":"/th?id=OHR.LanyonQuoit_ROW1211200542",
            "copyright":"Lanyon Quoit, Cornwall, England (© Guy Edwardes/Minden Pictures)",
            "copyrightlink":"https://www.bing.com/search?q=lanyon+quoit+cornwall&form=hpcapt",
            "title":"Info",
            "quiz":"/search?q=Bing+homepage+quiz&filters=WQOskey:%22HPQuiz_20220314_LanyonQuoit%22&FORM=HPQUIZ",
            "wp":true,
            "hsh":"13884c0db8f5f7b10c81944abc60908e",
            "drk":1,
            "top":1,
            "bot":1,
            "hs":[]
        }
    ],
    "jp":[
        {
            "startdate":"20220314",
            "fullstartdate":"202203141500",
            "enddate":"20220315",
            "url":"/th?id=OHR.RomanView_JA-JP7301817584_1920x1080.jpg&rf=LaDigue_1920x1080.jpg&pid=hp",
            "urlbase":"/th?id=OHR.RomanView_JA-JP7301817584",
            "copyright":"フォロ・ロマーノ, イタリア ローマ (© Peter Zelei Images/Getty Images)",
            "copyrightlink":"https://www.bing.com/search?q=%E3%83%95%E3%82%A9%E3%83%AD%E3%83%BB%E3%83%AD%E3%83%9E%E3%83%BC%E3%83%8E&form=hpcapt&filters=HpDate%3a%2220220314_1500%22",
            "title":"今日は「アイズ・オブ・マーチ」",
            "quiz":"/search?q=Bing+homepage+quiz&filters=WQOskey:%22HPQuiz_20220314_RomanView%22&FORM=HPQUIZ",
            "wp":true,
            "hsh":"d91a58d91e35bb2a486b4ae4bb78570d",
            "drk":1,
            "top":1,
            "bot":1,
            "hs":[]
        }
    ],
    "kr":[
        {
            "startdate":"20220314",
            "fullstartdate":"202203140700",
            "enddate":"20220315",
            "url":"/th?id=OHR.LanyonQuoit_ROW1211200542_1920x1080.jpg&rf=LaDigue_1920x1080.jpg&pid=hp",
            "urlbase":"/th?id=OHR.LanyonQuoit_ROW1211200542",
            "copyright":"Lanyon Quoit, Cornwall, England (© Guy Edwardes/Minden Pictures)",
            "copyrightlink":"https://www.bing.com/search?q=lanyon+quoit+cornwall&form=hpcapt",
            "title":"Info",
            "quiz":"/search?q=Bing+homepage+quiz&filters=WQOskey:%22HPQuiz_20220314_LanyonQuoit%22&FORM=HPQUIZ",
            "wp":true,
            "hsh":"13884c0db8f5f7b10c81944abc60908e",
            "drk":1,
            "top":1,
            "bot":1,
            "hs":[]
        }
    ],
    "nl":[
        {
            "startdate":"20220314",
            "fullstartdate":"202203140700",
            "enddate":"20220315",
            "url":"/th?id=OHR.LanyonQuoit_ROW1211200542_1920x1080.jpg&rf=LaDigue_1920x1080.jpg&pid=hp",
            "urlbase":"/th?id=OHR.LanyonQuoit_ROW1211200542",
            "copyright":"Lanyon Quoit, Cornwall, England (© Guy Edwardes/Minden Pictures)",
            "copyrightlink":"https://www.bing.com/search?q=lanyon+quoit+cornwall&form=hpcapt",
            "title":"Info",
            "quiz":"/search?q=Bing+homepage+quiz&filters=WQOskey:%22HPQuiz_20220314_LanyonQuoit%22&FORM=HPQUIZ",
            "wp":true,
            "hsh":"13884c0db8f5f7b10c81944abc60908e",
            "drk":1,
            "top":1,
            "bot":1,
            "hs":[]
        }
    ],
    "no":[
        {
            "startdate":"20220314",
            "fullstartdate":"202203140700",
            "enddate":"20220315",
            "url":"/th?id=OHR.LanyonQuoit_ROW1211200542_1920x1080.jpg&rf=LaDigue_1920x1080.jpg&pid=hp",
            "urlbase":"/th?id=OHR.LanyonQuoit_ROW1211200542",
            "copyright":"Lanyon Quoit, Cornwall, England (© Guy Edwardes/Minden Pictures)",
            "copyrightlink":"https://www.bing.com/search?q=lanyon+quoit+cornwall&form=hpcapt",
            "title":"Info",
            "quiz":"/search?q=Bing+homepage+quiz&filters=WQOskey:%22HPQuiz_20220314_LanyonQuoit%22&FORM=HPQUIZ",
            "wp":true,
            "hsh":"13884c0db8f5f7b10c81944abc60908e",
            "drk":1,
            "top":1,
            "bot":1,
            "hs":[]
        }
    ],
    "nz":[
        {
            "startdate":"20220314",
            "fullstartdate":"202203140700",
            "enddate":"20220315",
            "url":"/th?id=OHR.LanyonQuoit_ROW1211200542_1920x1080.jpg&rf=LaDigue_1920x1080.jpg&pid=hp",
            "urlbase":"/th?id=OHR.LanyonQuoit_ROW1211200542",
            "copyright":"Lanyon Quoit, Cornwall, England (© Guy Edwardes/Minden Pictures)",
            "copyrightlink":"https://www.bing.com/search?q=lanyon+quoit+cornwall&form=hpcapt",
            "title":"Info",
            "quiz":"/search?q=Bing+homepage+quiz&filters=WQOskey:%22HPQuiz_20220314_LanyonQuoit%22&FORM=HPQUIZ",
            "wp":true,
            "hsh":"13884c0db8f5f7b10c81944abc60908e",
            "drk":1,
            "top":1,
            "bot":1,
            "hs":[]
        }
    ],
    "ph":[
        {
            "startdate":"20220314",
            "fullstartdate":"202203140700",
            "enddate":"20220315",
            "url":"/th?id=OHR.LanyonQuoit_ROW1211200542_1920x1080.jpg&rf=LaDigue_1920x1080.jpg&pid=hp",
            "urlbase":"/th?id=OHR.LanyonQuoit_ROW1211200542",
            "copyright":"Lanyon Quoit, Cornwall, England (© Guy Edwardes/Minden Pictures)",
            "copyrightlink":"https://www.bing.com/search?q=lanyon+quoit+cornwall&form=hpcapt",
            "title":"Info",
            "quiz":"/search?q=Bing+homepage+quiz&filters=WQOskey:%22HPQuiz_20220314_LanyonQuoit%22&FORM=HPQUIZ",
            "wp":true,
            "hsh":"13884c0db8f5f7b10c81944abc60908e",
            "drk":1,
            "top":1,
            "bot":1,
            "hs":[]
        }
    ],
    "pt":[
        {
            "startdate":"20220314",
            "fullstartdate":"202203140700",
            "enddate":"20220315",
            "url":"/th?id=OHR.LanyonQuoit_ROW1211200542_1920x1080.jpg&rf=LaDigue_1920x1080.jpg&pid=hp",
            "urlbase":"/th?id=OHR.LanyonQuoit_ROW1211200542",
            "copyright":"Lanyon Quoit, Cornwall, England (© Guy Edwardes/Minden Pictures)",
            "copyrightlink":"https://www.bing.com/search?q=lanyon+quoit+cornwall&form=hpcapt",
            "title":"Info",
            "quiz":"/search?q=Bing+homepage+quiz&filters=WQOskey:%22HPQuiz_20220314_LanyonQuoit%22&FORM=HPQUIZ",
            "wp":true,
            "hsh":"13884c0db8f5f7b10c81944abc60908e",
            "drk":1,
            "top":1,
            "bot":1,
            "hs":[]
        }
    ],
    "ru":[
        {
            "startdate":"20220314",
            "fullstartdate":"202203140700",
            "enddate":"20220315",
            "url":"/th?id=OHR.LanyonQuoit_ROW1211200542_1920x1080.jpg&rf=LaDigue_1920x1080.jpg&pid=hp",
            "urlbase":"/th?id=OHR.LanyonQuoit_ROW1211200542",
            "copyright":"Lanyon Quoit, Cornwall, England (© Guy Edwardes/Minden Pictures)",
            "copyrightlink":"https://www.bing.com/search?q=lanyon+quoit+cornwall&form=hpcapt",
            "title":"Info",
            "quiz":"/search?q=Bing+homepage+quiz&filters=WQOskey:%22HPQuiz_20220314_LanyonQuoit%22&FORM=HPQUIZ",
            "wp":true,
            "hsh":"13884c0db8f5f7b10c81944abc60908e",
            "drk":1,
            "top":1,
            "bot":1,
            "hs":[]
        }
    ],
    "se":[
        {
            "startdate":"20220314",
            "fullstartdate":"202203140700",
            "enddate":"20220315",
            "url":"/th?id=OHR.LanyonQuoit_ROW1211200542_1920x1080.jpg&rf=LaDigue_1920x1080.jpg&pid=hp",
            "urlbase":"/th?id=OHR.LanyonQuoit_ROW1211200542",
            "copyright":"Lanyon Quoit, Cornwall, England (© Guy Edwardes/Minden Pictures)",
            "copyrightlink":"https://www.bing.com/search?q=lanyon+quoit+cornwall&form=hpcapt",
            "title":"Info",
            "quiz":"/search?q=Bing+homepage+quiz&filters=WQOskey:%22HPQuiz_20220314_LanyonQuoit%22&FORM=HPQUIZ",
            "wp":true,
            "hsh":"13884c0db8f5f7b10c81944abc60908e",
            "drk":1,
            "top":1,
            "bot":1,
            "hs":[]
        }
    ],
    "sg":[
        {
            "startdate":"20220314",
            "fullstartdate":"202203140700",
            "enddate":"20220315",
            "url":"/th?id=OHR.LanyonQuoit_ROW1211200542_1920x1080.jpg&rf=LaDigue_1920x1080.jpg&pid=hp",
            "urlbase":"/th?id=OHR.LanyonQuoit_ROW1211200542",
            "copyright":"Lanyon Quoit, Cornwall, England (© Guy Edwardes/Minden Pictures)",
            "copyrightlink":"https://www.bing.com/search?q=lanyon+quoit+cornwall&form=hpcapt",
            "title":"Info",
            "quiz":"/search?q=Bing+homepage+quiz&filters=WQOskey:%22HPQuiz_20220314_LanyonQuoit%22&FORM=HPQUIZ",
            "wp":true,
            "hsh":"13884c0db8f5f7b10c81944abc60908e",
            "drk":1,
            "top":1,
            "bot":1,
            "hs":[]
        }
    ],
    "tw":[
        {
            "startdate":"20220314",
            "fullstartdate":"202203140700",
            "enddate":"20220315",
            "url":"/th?id=OHR.LanyonQuoit_ROW1211200542_1920x1080.jpg&rf=LaDigue_1920x1080.jpg&pid=hp",
            "urlbase":"/th?id=OHR.LanyonQuoit_ROW1211200542",
            "copyright":"Lanyon Quoit, Cornwall, England (© Guy Edwardes/Minden Pictures)",
            "copyrightlink":"https://www.bing.com/search?q=lanyon+quoit+cornwall&form=hpcapt",
            "title":"Info",
            "quiz":"/search?q=Bing+homepage+quiz&filters=WQOskey:%22HPQuiz_20220314_LanyonQuoit%22&FORM=HPQUIZ",
            "wp":true,
            "hsh":"13884c0db8f5f7b10c81944abc60908e",
            "drk":1,
            "top":1,
            "bot":1,
            "hs":[]
        }
    ],
    "uk":[
        {
            "startdate":"20220313",
            "fullstartdate":"202203132300",
            "enddate":"20220314",
            "url":"/th?id=OHR.LanyonQuoit_DE-DE2402126177_1920x1080.jpg&rf=LaDigue_1920x1080.jpg&pid=hp",
            "urlbase":"/th?id=OHR.LanyonQuoit_DE-DE2402126177",
            "copyright":"Das Großsteingrab Lanyon Quoit in Cornwall, England, Vereinigtes Königreich (© Guy Edwardes/Minden Pictures)",
            "copyrightlink":"https://www.bing.com/search?q=Pi-Tag&form=hpcapt&filters=HpDate%3a%2220220313_2300%22",
            "title":"Welche Zahl wird heute gefeiert?",
            "quiz":"/search?q=Bing+homepage+quiz&filters=WQOskey:%22HPQuiz_20220313_LanyonQuoit%22&FORM=HPQUIZ",
            "wp":true,
            "hsh":"9f11988b205aef427ee7a7002509d48d",
            "drk":1,
            "top":1,
            "bot":1,
            "hs":[]
        }
    ]
}