{
    "ar":[
        {
            "startdate":"20231026",
            "fullstartdate":"202310260700",
            "enddate":"20231027",
            "url":"/th?id=OHR.ViennaAutumn_ROW6120946302_1920x1080.jpg&rf=LaDigue_1920x1080.jpg&pid=hp",
            "urlbase":"/th?id=OHR.ViennaAutumn_ROW6120946302",
            "copyright":"Autumn foliage in Schönbrunn Palace Park, Vienna, Austria (© rusm/Getty Images)",
            "copyrightlink":"https://www.bing.com/search?q=Sch%C3%B6nbrunn+Palace+Park+Vienna&form=hpcapt",
            "title":"Info",
            "quiz":"/search?q=Bing+homepage+quiz&filters=WQOskey:%22HPQuiz_20231026_ViennaAutumn%22&FORM=HPQUIZ",
            "wp":true,
            "hsh":"44ffede44c5e22aadbba0907a08e6958",
            "drk":1,
            "top":1,
            "bot":1,
            "hs":[]
        }
    ],
    "at":[
        {
            "startdate":"20231026",
            "fullstartdate":"202310260700",
            "enddate":"20231027",
            "url":"/th?id=OHR.ViennaAutumn_ROW6120946302_1920x1080.jpg&rf=LaDigue_1920x1080.jpg&pid=hp",
            "urlbase":"/th?id=OHR.ViennaAutumn_ROW6120946302",
            "copyright":"Autumn foliage in Schönbrunn Palace Park, Vienna, Austria (© rusm/Getty Images)",
            "copyrightlink":"https://www.bing.com/search?q=Sch%C3%B6nbrunn+Palace+Park+Vienna&form=hpcapt",
            "title":"Info",
            "quiz":"/search?q=Bing+homepage+quiz&filters=WQOskey:%22HPQuiz_20231026_ViennaAutumn%22&FORM=HPQUIZ",
            "wp":true,
            "hsh":"44ffede44c5e22aadbba0907a08e6958",
            "drk":1,
            "top":1,
            "bot":1,
            "hs":[]
        }
    ],
    "au":[
        {
            "startdate":"20231026",
            "fullstartdate":"202310260700",
            "enddate":"20231027",
            "url":"/th?id=OHR.ViennaAutumn_ROW6120946302_1920x1080.jpg&rf=LaDigue_1920x1080.jpg&pid=hp",
            "urlbase":"/th?id=OHR.ViennaAutumn_ROW6120946302",
            "copyright":"Autumn foliage in Schönbrunn Palace Park, Vienna, Austria (© rusm/Getty Images)",
            "copyrightlink":"https://www.bing.com/search?q=Sch%C3%B6nbrunn+Palace+Park+Vienna&form=hpcapt&filters=HpDate%3a%2220231026_0700%22",
            "title":"Info",
            "quiz":"/search?q=Bing+homepage+quiz&filters=WQOskey:%22HPQuiz_20231026_ViennaAutumn%22&FORM=HPQUIZ",
            "wp":true,
            "hsh":"44ffede44c5e22aadbba0907a08e6958",
            "drk":1,
            "top":1,
            "bot":1,
            "hs":[]
        }
    ],
    "be":[
        {
            "startdate":"20231026",
            "fullstartdate":"202310260700",
            "enddate":"20231027",
            "url":"/th?id=OHR.ViennaAutumn_ROW6120946302_1920x1080.jpg&rf=LaDigue_1920x1080.jpg&pid=hp",
            "urlbase":"/th?id=OHR.ViennaAutumn_ROW6120946302",
            "copyright":"Autumn foliage in Schönbrunn Palace Park, Vienna, Austria (© rusm/Getty Images)",
            "copyrightlink":"https://www.bing.com/search?q=Sch%C3%B6nbrunn+Palace+Park+Vienna&form=hpcapt",
            "title":"Info",
            "quiz":"/search?q=Bing+homepage+quiz&filters=WQOskey:%22HPQuiz_20231026_ViennaAutumn%22&FORM=HPQUIZ",
            "wp":true,
            "hsh":"44ffede44c5e22aadbba0907a08e6958",
            "drk":1,
            "top":1,
            "bot":1,
            "hs":[]
        }
    ],
    "br":[
        {
            "startdate":"20231026",
            "fullstartdate":"202310260300",
            "enddate":"20231027",
            "url":"/th?id=OHR.ViennaAutumn_PT-BR1572205142_1920x1080.jpg&rf=LaDigue_1920x1080.jpg&pid=hp",
            "urlbase":"/th?id=OHR.ViennaAutumn_PT-BR1572205142",
            "copyright":"Folhagem de outono no Parque do Palácio de Schönbrunn, Viena, Áustria (© rusm/Getty Images)",
            "copyrightlink":"https://www.bing.com/search?q=Parque+do+Pal%C3%A1cio+de+Sch%C3%B6nbrunn+Viena&form=hpcapt&mkt=pt-br",
            "title":"Um paraíso para os amantes de folhas",
            "quiz":"/search?q=Bing+homepage+quiz&filters=WQOskey:%22HPQuiz_20231026_ViennaAutumn%22&FORM=HPQUIZ",
            "wp":true,
            "hsh":"2e404614763c741da6348327abfb5de2",
            "drk":1,
            "top":1,
            "bot":1,
            "hs":[]
        }
    ],
    "ca":[
        {
            "startdate":"20231026",
            "fullstartdate":"202310260400",
            "enddate":"20231027",
            "url":"/th?id=OHR.ViennaAutumn_EN-CA8786180310_1920x1080.jpg&rf=LaDigue_1920x1080.jpg&pid=hp",
            "urlbase":"/th?id=OHR.ViennaAutumn_EN-CA8786180310",
            "copyright":"Autumn foliage in Schönbrunn Palace Park, Vienna, Austria (© rusm/Getty Images)",
            "copyrightlink":"https://www.bing.com/search?q=Sch%C3%B6nbrunn+Palace+Park+Vienna&form=hpcapt&filters=HpDate%3a%2220231026_0400%22",
            "title":"A leaf stomper's paradise",
            "quiz":"/search?q=Bing+homepage+quiz&filters=WQOskey:%22HPQuiz_20231026_ViennaAutumn%22&FORM=HPQUIZ",
            "wp":true,
            "hsh":"44d1117e167e160b867fac29826ff775",
            "drk":1,
            "top":1,
            "bot":1,
            "hs":[]
        }
    ],
    "ch":[
        {
            "startdate":"20231026",
            "fullstartdate":"202310260700",
            "enddate":"20231027",
            "url":"/th?id=OHR.ViennaAutumn_ROW6120946302_1920x1080.jpg&rf=LaDigue_1920x1080.jpg&pid=hp",
            "urlbase":"/th?id=OHR.ViennaAutumn_ROW6120946302",
            "copyright":"Autumn foliage in Schönbrunn Palace Park, Vienna, Austria (© rusm/Getty Images)",
            "copyrightlink":"https://www.bing.com/search?q=Sch%C3%B6nbrunn+Palace+Park+Vienna&form=hpcapt",
            "title":"Info",
            "quiz":"/search?q=Bing+homepage+quiz&filters=WQOskey:%22HPQuiz_20231026_ViennaAutumn%22&FORM=HPQUIZ",
            "wp":true,
            "hsh":"44ffede44c5e22aadbba0907a08e6958",
            "drk":1,
            "top":1,
            "bot":1,
            "hs":[]
        }
    ],
    "cl":[
        {
            "startdate":"20231026",
            "fullstartdate":"202310260700",
            "enddate":"20231027",
            "url":"/th?id=OHR.ViennaAutumn_ROW6120946302_1920x1080.jpg&rf=LaDigue_1920x1080.jpg&pid=hp",
            "urlbase":"/th?id=OHR.ViennaAutumn_ROW6120946302",
            "copyright":"Autumn foliage in Schönbrunn Palace Park, Vienna, Austria (© rusm/Getty Images)",
            "copyrightlink":"https://www.bing.com/search?q=Sch%C3%B6nbrunn+Palace+Park+Vienna&form=hpcapt",
            "title":"Info",
            "quiz":"/search?q=Bing+homepage+quiz&filters=WQOskey:%22HPQuiz_20231026_ViennaAutumn%22&FORM=HPQUIZ",
            "wp":true,
            "hsh":"44ffede44c5e22aadbba0907a08e6958",
            "drk":1,
            "top":1,
            "bot":1,
            "hs":[]
        }
    ],
    "cn":[
        {
            "startdate":"20231026",
            "fullstartdate":"202310261600",
            "enddate":"20231027",
            "url":"/th?id=OHR.OldBridgeSkye_ZH-CN7228411986_1920x1080.jpg&rf=LaDigue_1920x1080.jpg&pid=hp",
            "urlbase":"/th?id=OHR.OldBridgeSkye_ZH-CN7228411986",
            "copyright":"斯利加坎老桥，苏格兰斯凯岛 (© Aliaume Chapelle/Tandem Stills + Motion)",
            "copyrightlink":"https://www.bing.com/search?q=%E8%8B%8F%E6%A0%BC%E5%85%B0%E6%96%AF%E5%87%AF%E5%B2%9B&form=hpcapt&mkt=zh-cn",
            "title":"魔法之河深不见底",
            "quiz":"/search?q=Bing+homepage+quiz&filters=WQOskey:%22HPQuiz_20231026_OldBridgeSkye%22&FORM=HPQUIZ",
            "wp":true,
            "hsh":"05317e648ed3394bd3d6349dc7ad2217",
            "drk":1,
            "top":1,
            "bot":1,
            "hs":[]
        }
    ],
    "de":[
        {
            "startdate":"20231025",
            "fullstartdate":"202310252200",
            "enddate":"20231026",
            "url":"/th?id=OHR.ViennaAutumn_DE-DE4206809652_1920x1080.jpg&rf=LaDigue_1920x1080.jpg&pid=hp",
            "urlbase":"/th?id=OHR.ViennaAutumn_DE-DE4206809652",
            "copyright":"Herbstlaub im Schlosspark Schönbrunn, Wien, Österreich (© rusm/Getty Images)",
            "copyrightlink":"https://www.bing.com/search?q=Schloss+Sch%C3%B6nbrunn&form=hpcapt&filters=HpDate%3a%2220231025_2200%22",
            "title":"Herbstliche Allee im Schlosspark Schönbrunn",
            "quiz":"/search?q=Bing+homepage+quiz&filters=WQOskey:%22HPQuiz_20231025_ViennaAutumn%22&FORM=HPQUIZ",
            "wp":true,
            "hsh":"32f6ff04e9b19f8bf16c85a05ce2f167",
            "drk":1,
            "top":1,
            "bot":1,
            "hs":[]
        }
    ],
    "dk":[
        {
            "startdate":"20231026",
            "fullstartdate":"202310260700",
            "enddate":"20231027",
            "url":"/th?id=OHR.ViennaAutumn_ROW6120946302_1920x1080.jpg&rf=LaDigue_1920x1080.jpg&pid=hp",
            "urlbase":"/th?id=OHR.ViennaAutumn_ROW6120946302",
            "copyright":"Autumn foliage in Schönbrunn Palace Park, Vienna, Austria (© rusm/Getty Images)",
            "copyrightlink":"https://www.bing.com/search?q=Sch%C3%B6nbrunn+Palace+Park+Vienna&form=hpcapt",
            "title":"Info",
            "quiz":"/search?q=Bing+homepage+quiz&filters=WQOskey:%22HPQuiz_20231026_ViennaAutumn%22&FORM=HPQUIZ",
            "wp":true,
            "hsh":"44ffede44c5e22aadbba0907a08e6958",
            "drk":1,
            "top":1,
            "bot":1,
            "hs":[]
        }
    ],
    "es":[
        {
            "startdate":"20231025",
            "fullstartdate":"202310252200",
            "enddate":"20231026",
            "url":"/th?id=OHR.ViennaAutumn_ES-ES4797164251_1920x1080.jpg&rf=LaDigue_1920x1080.jpg&pid=hp",
            "urlbase":"/th?id=OHR.ViennaAutumn_ES-ES4797164251",
            "copyright":"Bosque otoñal en el parque del palacio de Schönbrunn, Viena, Austria (© rusm/Getty Images)",
            "copyrightlink":"https://www.bing.com/search?q=Palacio+de+Sch%C3%B6nbrunn+Viena&form=hpcapt&filters=HpDate%3a%2220231025_2200%22",
            "title":"El paraíso de los que pisotean las hojas",
            "quiz":"/search?q=Bing+homepage+quiz&filters=WQOskey:%22HPQuiz_20231025_ViennaAutumn%22&FORM=HPQUIZ",
            "wp":true,
            "hsh":"098b29f0e13528a2f0b6e39c54c4ebbd",
            "drk":1,
            "top":1,
            "bot":1,
            "hs":[]
        }
    ],
    "fi":[
        {
            "startdate":"20231026",
            "fullstartdate":"202310260700",
            "enddate":"20231027",
            "url":"/th?id=OHR.ViennaAutumn_ROW6120946302_1920x1080.jpg&rf=LaDigue_1920x1080.jpg&pid=hp",
            "urlbase":"/th?id=OHR.ViennaAutumn_ROW6120946302",
            "copyright":"Autumn foliage in Schönbrunn Palace Park, Vienna, Austria (© rusm/Getty Images)",
            "copyrightlink":"https://www.bing.com/search?q=Sch%C3%B6nbrunn+Palace+Park+Vienna&form=hpcapt",
            "title":"Info",
            "quiz":"/search?q=Bing+homepage+quiz&filters=WQOskey:%22HPQuiz_20231026_ViennaAutumn%22&FORM=HPQUIZ",
            "wp":true,
            "hsh":"44ffede44c5e22aadbba0907a08e6958",
            "drk":1,
            "top":1,
            "bot":1,
            "hs":[]
        }
    ],
    "fr":[
        {
            "startdate":"20231025",
            "fullstartdate":"202310252200",
            "enddate":"20231026",
            "url":"/th?id=OHR.ViennaAutumn_FR-FR6349704805_1920x1080.jpg&rf=LaDigue_1920x1080.jpg&pid=hp",
            "urlbase":"/th?id=OHR.ViennaAutumn_FR-FR6349704805",
            "copyright":"Feuillage d'automne dans le parc du château de Schönbrunn, Vienne, Autriche (© rusm/Getty Images)",
            "copyrightlink":"https://www.bing.com/search?q=ch%C3%A2teau+de+Sch%C3%B6nbrunn+&form=hpcapt&filters=HpDate%3a%2220231025_2200%22",
            "title":"Un paysage de conte de fées",
            "quiz":"/search?q=Bing+homepage+quiz&filters=WQOskey:%22HPQuiz_20231025_ViennaAutumn%22&FORM=HPQUIZ",
            "wp":true,
            "hsh":"faa73e2d17bda7a601222d1c8db9cb5f",
            "drk":1,
            "top":1,
            "bot":1,
            "hs":[]
        }
    ],
    "hk":[
        {
            "startdate":"20231026",
            "fullstartdate":"202310260700",
            "enddate":"20231027",
            "url":"/th?id=OHR.ViennaAutumn_ROW6120946302_1920x1080.jpg&rf=LaDigue_1920x1080.jpg&pid=hp",
            "urlbase":"/th?id=OHR.ViennaAutumn_ROW6120946302",
            "copyright":"Autumn foliage in Schönbrunn Palace Park, Vienna, Austria (© rusm/Getty Images)",
            "copyrightlink":"https://www.bing.com/search?q=Sch%C3%B6nbrunn+Palace+Park+Vienna&form=hpcapt",
            "title":"Info",
            "quiz":"/search?q=Bing+homepage+quiz&filters=WQOskey:%22HPQuiz_20231026_ViennaAutumn%22&FORM=HPQUIZ",
            "wp":true,
            "hsh":"44ffede44c5e22aadbba0907a08e6958",
            "drk":1,
            "top":1,
            "bot":1,
            "hs":[]
        }
    ],
    "ie":[
        {
            "startdate":"20231026",
            "fullstartdate":"202310260700",
            "enddate":"20231027",
            "url":"/th?id=OHR.ViennaAutumn_ROW6120946302_1920x1080.jpg&rf=LaDigue_1920x1080.jpg&pid=hp",
            "urlbase":"/th?id=OHR.ViennaAutumn_ROW6120946302",
            "copyright":"Autumn foliage in Schönbrunn Palace Park, Vienna, Austria (© rusm/Getty Images)",
            "copyrightlink":"https://www.bing.com/search?q=Sch%C3%B6nbrunn+Palace+Park+Vienna&form=hpcapt",
            "title":"Info",
            "quiz":"/search?q=Bing+homepage+quiz&filters=WQOskey:%22HPQuiz_20231026_ViennaAutumn%22&FORM=HPQUIZ",
            "wp":true,
            "hsh":"44ffede44c5e22aadbba0907a08e6958",
            "drk":1,
            "top":1,
            "bot":1,
            "hs":[]
        }
    ],
    "in":[
        {
            "startdate":"20231025",
            "fullstartdate":"202310251830",
            "enddate":"20231026",
            "url":"/th?id=OHR.ViennaAutumn_EN-IN5923148753_1920x1080.jpg&rf=LaDigue_1920x1080.jpg&pid=hp",
            "urlbase":"/th?id=OHR.ViennaAutumn_EN-IN5923148753",
            "copyright":"Autumn foliage in Schönbrunn Palace Park, Vienna, Austria (© rusm/Getty Images)",
            "copyrightlink":"https://www.bing.com/search?q=Sch%C3%B6nbrunn+Palace+Park+Vienna&form=hpcapt&filters=HpDate%3a%2220231025_1830%22",
            "title":"A leaf stomper's paradise",
            "quiz":"/search?q=Bing+homepage+quiz&filters=WQOskey:%22HPQuiz_20231025_ViennaAutumn%22&FORM=HPQUIZ",
            "wp":true,
            "hsh":"9e67166d5a0f4e51944d64918b2a89ac",
            "drk":1,
            "top":1,
            "bot":1,
            "hs":[]
        }
    ],
    "it":[
        {
            "startdate":"20231025",
            "fullstartdate":"202310252200",
            "enddate":"20231026",
            "url":"/th?id=OHR.ViennaAutumn_IT-IT9164239542_1920x1080.jpg&rf=LaDigue_1920x1080.jpg&pid=hp",
            "urlbase":"/th?id=OHR.ViennaAutumn_IT-IT9164239542",
            "copyright":"Fogliame autunnale nel parco del Castello di Schönbrunn (© rusm/Getty Images)",
            "copyrightlink":"https://www.bing.com/search?q=il+Castello+di+Sch%C3%B6nbrunn+dov%27%C3%A8&form=hpcapt",
            "title":"Un fogliame da favola!",
            "quiz":"/search?q=Bing+homepage+quiz&filters=WQOskey:%22HPQuiz_20231025_ViennaAutumn%22&FORM=HPQUIZ",
            "wp":true,
            "hsh":"baf9891743327ebfc645ba0e937dff96",
            "drk":1,
            "top":1,
            "bot":1,
            "hs":[]
        }
    ],
    "jp":[
        {
            "startdate":"20231026",
            "fullstartdate":"202310261500",
            "enddate":"20231027",
            "url":"/th?id=OHR.OldBridgeSkye_JA-JP3696006091_1920x1080.jpg&rf=LaDigue_1920x1080.jpg&pid=hp",
            "urlbase":"/th?id=OHR.OldBridgeSkye_JA-JP3696006091",
            "copyright":"スカイ島のスリガチャン・オールド・ブリッジ, スコットランド (© Aliaume Chapelle/Tandem Stills + Motion)",
            "copyrightlink":"https://www.bing.com/search?q=%E3%82%B9%E3%82%AB%E3%82%A4%E5%B3%B6%E3%81%AE%E3%82%B9%E3%83%AA%E3%82%AC%E3%83%81%E3%83%A3%E3%83%B3%E3%83%BB%E3%82%AA%E3%83%BC%E3%83%AB%E3%83%89%E3%83%BB%E3%83%96%E3%83%AA%E3%83%83%E3%82%B8&form=hpcapt&filters=HpDate%3a%2220231026_1500%22",
            "title":"歴史的な石造りの橋",
            "quiz":"/search?q=Bing+homepage+quiz&filters=WQOskey:%22HPQuiz_20231026_OldBridgeSkye%22&FORM=HPQUIZ",
            "wp":true,
            "hsh":"59ebc9efe02900644b30b42cf8151b11",
            "drk":1,
            "top":1,
            "bot":1,
            "hs":[]
        }
    ],
    "kr":[
        {
            "startdate":"20231026",
            "fullstartdate":"202310260700",
            "enddate":"20231027",
            "url":"/th?id=OHR.ViennaAutumn_ROW6120946302_1920x1080.jpg&rf=LaDigue_1920x1080.jpg&pid=hp",
            "urlbase":"/th?id=OHR.ViennaAutumn_ROW6120946302",
            "copyright":"Autumn foliage in Schönbrunn Palace Park, Vienna, Austria (© rusm/Getty Images)",
            "copyrightlink":"https://www.bing.com/search?q=Sch%C3%B6nbrunn+Palace+Park+Vienna&form=hpcapt",
            "title":"Info",
            "quiz":"/search?q=Bing+homepage+quiz&filters=WQOskey:%22HPQuiz_20231026_ViennaAutumn%22&FORM=HPQUIZ",
            "wp":true,
            "hsh":"44ffede44c5e22aadbba0907a08e6958",
            "drk":1,
            "top":1,
            "bot":1,
            "hs":[]
        }
    ],
    "nl":[
        {
            "startdate":"20231026",
            "fullstartdate":"202310260700",
            "enddate":"20231027",
            "url":"/th?id=OHR.ViennaAutumn_ROW6120946302_1920x1080.jpg&rf=LaDigue_1920x1080.jpg&pid=hp",
            "urlbase":"/th?id=OHR.ViennaAutumn_ROW6120946302",
            "copyright":"Autumn foliage in Schönbrunn Palace Park, Vienna, Austria (© rusm/Getty Images)",
            "copyrightlink":"https://www.bing.com/search?q=Sch%C3%B6nbrunn+Palace+Park+Vienna&form=hpcapt",
            "title":"Info",
            "quiz":"/search?q=Bing+homepage+quiz&filters=WQOskey:%22HPQuiz_20231026_ViennaAutumn%22&FORM=HPQUIZ",
            "wp":true,
            "hsh":"44ffede44c5e22aadbba0907a08e6958",
            "drk":1,
            "top":1,
            "bot":1,
            "hs":[]
        }
    ],
    "no":[
        {
            "startdate":"20231026",
            "fullstartdate":"202310260700",
            "enddate":"20231027",
            "url":"/th?id=OHR.ViennaAutumn_ROW6120946302_1920x1080.jpg&rf=LaDigue_1920x1080.jpg&pid=hp",
            "urlbase":"/th?id=OHR.ViennaAutumn_ROW6120946302",
            "copyright":"Autumn foliage in Schönbrunn Palace Park, Vienna, Austria (© rusm/Getty Images)",
            "copyrightlink":"https://www.bing.com/search?q=Sch%C3%B6nbrunn+Palace+Park+Vienna&form=hpcapt",
            "title":"Info",
            "quiz":"/search?q=Bing+homepage+quiz&filters=WQOskey:%22HPQuiz_20231026_ViennaAutumn%22&FORM=HPQUIZ",
            "wp":true,
            "hsh":"44ffede44c5e22aadbba0907a08e6958",
            "drk":1,
            "top":1,
            "bot":1,
            "hs":[]
        }
    ],
    "nz":[
        {
            "startdate":"20231026",
            "fullstartdate":"202310260700",
            "enddate":"20231027",
            "url":"/th?id=OHR.ViennaAutumn_ROW6120946302_1920x1080.jpg&rf=LaDigue_1920x1080.jpg&pid=hp",
            "urlbase":"/th?id=OHR.ViennaAutumn_ROW6120946302",
            "copyright":"Autumn foliage in Schönbrunn Palace Park, Vienna, Austria (© rusm/Getty Images)",
            "copyrightlink":"https://www.bing.com/search?q=Sch%C3%B6nbrunn+Palace+Park+Vienna&form=hpcapt",
            "title":"Info",
            "quiz":"/search?q=Bing+homepage+quiz&filters=WQOskey:%22HPQuiz_20231026_ViennaAutumn%22&FORM=HPQUIZ",
            "wp":true,
            "hsh":"44ffede44c5e22aadbba0907a08e6958",
            "drk":1,
            "top":1,
            "bot":1,
            "hs":[]
        }
    ],
    "ph":[
        {
            "startdate":"20231026",
            "fullstartdate":"202310260700",
            "enddate":"20231027",
            "url":"/th?id=OHR.ViennaAutumn_ROW6120946302_1920x1080.jpg&rf=LaDigue_1920x1080.jpg&pid=hp",
            "urlbase":"/th?id=OHR.ViennaAutumn_ROW6120946302",
            "copyright":"Autumn foliage in Schönbrunn Palace Park, Vienna, Austria (© rusm/Getty Images)",
            "copyrightlink":"https://www.bing.com/search?q=Sch%C3%B6nbrunn+Palace+Park+Vienna&form=hpcapt",
            "title":"Info",
            "quiz":"/search?q=Bing+homepage+quiz&filters=WQOskey:%22HPQuiz_20231026_ViennaAutumn%22&FORM=HPQUIZ",
            "wp":true,
            "hsh":"44ffede44c5e22aadbba0907a08e6958",
            "drk":1,
            "top":1,
            "bot":1,
            "hs":[]
        }
    ],
    "pt":[
        {
            "startdate":"20231026",
            "fullstartdate":"202310260700",
            "enddate":"20231027",
            "url":"/th?id=OHR.ViennaAutumn_ROW6120946302_1920x1080.jpg&rf=LaDigue_1920x1080.jpg&pid=hp",
            "urlbase":"/th?id=OHR.ViennaAutumn_ROW6120946302",
            "copyright":"Autumn foliage in Schönbrunn Palace Park, Vienna, Austria (© rusm/Getty Images)",
            "copyrightlink":"https://www.bing.com/search?q=Sch%C3%B6nbrunn+Palace+Park+Vienna&form=hpcapt",
            "title":"Info",
            "quiz":"/search?q=Bing+homepage+quiz&filters=WQOskey:%22HPQuiz_20231026_ViennaAutumn%22&FORM=HPQUIZ",
            "wp":true,
            "hsh":"44ffede44c5e22aadbba0907a08e6958",
            "drk":1,
            "top":1,
            "bot":1,
            "hs":[]
        }
    ],
    "ru":[
        {
            "startdate":"20231026",
            "fullstartdate":"202310260700",
            "enddate":"20231027",
            "url":"/th?id=OHR.ViennaAutumn_ROW6120946302_1920x1080.jpg&rf=LaDigue_1920x1080.jpg&pid=hp",
            "urlbase":"/th?id=OHR.ViennaAutumn_ROW6120946302",
            "copyright":"Autumn foliage in Schönbrunn Palace Park, Vienna, Austria (© rusm/Getty Images)",
            "copyrightlink":"https://www.bing.com/search?q=Sch%C3%B6nbrunn+Palace+Park+Vienna&form=hpcapt",
            "title":"Info",
            "quiz":"/search?q=Bing+homepage+quiz&filters=WQOskey:%22HPQuiz_20231026_ViennaAutumn%22&FORM=HPQUIZ",
            "wp":true,
            "hsh":"44ffede44c5e22aadbba0907a08e6958",
            "drk":1,
            "top":1,
            "bot":1,
            "hs":[]
        }
    ],
    "se":[
        {
            "startdate":"20231026",
            "fullstartdate":"202310260700",
            "enddate":"20231027",
            "url":"/th?id=OHR.ViennaAutumn_ROW6120946302_1920x1080.jpg&rf=LaDigue_1920x1080.jpg&pid=hp",
            "urlbase":"/th?id=OHR.ViennaAutumn_ROW6120946302",
            "copyright":"Autumn foliage in Schönbrunn Palace Park, Vienna, Austria (© rusm/Getty Images)",
            "copyrightlink":"https://www.bing.com/search?q=Sch%C3%B6nbrunn+Palace+Park+Vienna&form=hpcapt",
            "title":"Info",
            "quiz":"/search?q=Bing+homepage+quiz&filters=WQOskey:%22HPQuiz_20231026_ViennaAutumn%22&FORM=HPQUIZ",
            "wp":true,
            "hsh":"44ffede44c5e22aadbba0907a08e6958",
            "drk":1,
            "top":1,
            "bot":1,
            "hs":[]
        }
    ],
    "sg":[
        {
            "startdate":"20231026",
            "fullstartdate":"202310260700",
            "enddate":"20231027",
            "url":"/th?id=OHR.ViennaAutumn_ROW6120946302_1920x1080.jpg&rf=LaDigue_1920x1080.jpg&pid=hp",
            "urlbase":"/th?id=OHR.ViennaAutumn_ROW6120946302",
            "copyright":"Autumn foliage in Schönbrunn Palace Park, Vienna, Austria (© rusm/Getty Images)",
            "copyrightlink":"https://www.bing.com/search?q=Sch%C3%B6nbrunn+Palace+Park+Vienna&form=hpcapt",
            "title":"Info",
            "quiz":"/search?q=Bing+homepage+quiz&filters=WQOskey:%22HPQuiz_20231026_ViennaAutumn%22&FORM=HPQUIZ",
            "wp":true,
            "hsh":"44ffede44c5e22aadbba0907a08e6958",
            "drk":1,
            "top":1,
            "bot":1,
            "hs":[]
        }
    ],
    "tw":[
        {
            "startdate":"20231026",
            "fullstartdate":"202310260700",
            "enddate":"20231027",
            "url":"/th?id=OHR.ViennaAutumn_ROW6120946302_1920x1080.jpg&rf=LaDigue_1920x1080.jpg&pid=hp",
            "urlbase":"/th?id=OHR.ViennaAutumn_ROW6120946302",
            "copyright":"Autumn foliage in Schönbrunn Palace Park, Vienna, Austria (© rusm/Getty Images)",
            "copyrightlink":"https://www.bing.com/search?q=Sch%C3%B6nbrunn+Palace+Park+Vienna&form=hpcapt",
            "title":"Info",
            "quiz":"/search?q=Bing+homepage+quiz&filters=WQOskey:%22HPQuiz_20231026_ViennaAutumn%22&FORM=HPQUIZ",
            "wp":true,
            "hsh":"44ffede44c5e22aadbba0907a08e6958",
            "drk":1,
            "top":1,
            "bot":1,
            "hs":[]
        }
    ],
    "uk":[
        {
            "startdate":"20231026",
            "fullstartdate":"202310261500",
            "enddate":"20231027",
            "url":"/th?id=OHR.OldBridgeSkye_JA-JP3696006091_1920x1080.jpg&rf=LaDigue_1920x1080.jpg&pid=hp",
            "urlbase":"/th?id=OHR.OldBridgeSkye_JA-JP3696006091",
            "copyright":"スカイ島のスリガチャン・オールド・ブリッジ, スコットランド (© Aliaume Chapelle/Tandem Stills + Motion)",
            "copyrightlink":"https://www.bing.com/search?q=%E3%82%B9%E3%82%AB%E3%82%A4%E5%B3%B6%E3%81%AE%E3%82%B9%E3%83%AA%E3%82%AC%E3%83%81%E3%83%A3%E3%83%B3%E3%83%BB%E3%82%AA%E3%83%BC%E3%83%AB%E3%83%89%E3%83%BB%E3%83%96%E3%83%AA%E3%83%83%E3%82%B8&form=hpcapt&filters=HpDate%3a%2220231026_1500%22",
            "title":"歴史的な石造りの橋",
            "quiz":"/search?q=Bing+homepage+quiz&filters=WQOskey:%22HPQuiz_20231026_OldBridgeSkye%22&FORM=HPQUIZ",
            "wp":true,
            "hsh":"59ebc9efe02900644b30b42cf8151b11",
            "drk":1,
            "top":1,
            "bot":1,
            "hs":[]
        }
    ]
}